LICENSE
README.md
magic_specs/__init__.py
magic_specs/_batched.py
magic_specs/_definition.py
magic_specs/_import_from_string.py
magic_specs/_iterable_cache.py
magic_specs/_ttl_cache.py
magic_specs/py.typed
magic_specs-0.0.8.dist-info/LICENSE
magic_specs-0.0.8.dist-info/METADATA
magic_specs-0.0.8.dist-info/WHEEL
magic_specs-0.0.8.dist-info/RECORD
