Metadata-Version: 2.1
Name: magic-specs
Version: 0.0.8
Summary: 
Home-page: https://github.com/MrThearMan/magic-specs
License: MIT
Author: Matti Lamppu
Author-email: lamppu.matti.akseli@gmail.com
Requires-Python: >=3.8,<4
Classifier: Intended Audience :: Developers
Classifier: License :: OSI Approved :: MIT License
Classifier: Natural Language :: English
Classifier: Programming Language :: Python
Classifier: Programming Language :: Python :: 3
Classifier: Programming Language :: Python :: 3.8
Classifier: Programming Language :: Python :: 3.9
Classifier: Programming Language :: Python :: 3.10
Classifier: Programming Language :: Python :: 3.11
Classifier: Programming Language :: Python :: 3.12
Classifier: Programming Language :: Python :: 3 :: Only
Project-URL: Bug Tracker, https://github.com/MrThearMan/magic-specs/issues
Project-URL: Repository, https://github.com/MrThearMan/magic-specs
